sthir/CLI.py
sthir/Test.py
sthir/__init__.py
sthir/convert_2p15.py
sthir/convert_byte.py
sthir/generate_search.py
sthir/mmh3.py
sthir/parse.py
sthir/scan.py
sthir/spectral_bloom_filter.py
sthir/js_utils/LICENSE.txt
sthir/js_utils/murmurhash3js.min.js
sthir/js_utils/utility.js
sthir/resources/LICENSE.md
sthir/resources/english_dict.txt
sthir-0.0.2.dist-info/LICENSE
sthir-0.0.2.dist-info/METADATA
sthir-0.0.2.dist-info/WHEEL
sthir-0.0.2.dist-info/entry_points.txt
sthir-0.0.2.dist-info/top_level.txt
sthir-0.0.2.dist-info/RECORD
