Metadata-Version: 2.1
Name: sthir
Version: 0.0.2
Summary: A package for creating Spectral Bloom filters for static sites
Home-page: https://github.com/pncnmnp/Spectral-Bloom-Search
Author: Parth Parikh, Dhruvam Kothari,Mrunank Mistry
Author-email: mrunankmistry52@gmail.com
License: UNKNOWN
Platform: UNKNOWN
Classifier: Programming Language :: Python :: 3
Classifier: License :: OSI Approved :: MIT License
Classifier: Operating System :: OS Independent
Requires-Python: >=3.6
Requires-Dist: nltk
Requires-Dist: bitarray
Requires-Dist: bs4
Requires-Dist: newspaper3k
Requires-Dist: lxml
Requires-Dist: requests
